README.md
setup.py
amazon_buy_bot/__init__.py
amazon_buy_bot.egg-info/PKG-INFO
amazon_buy_bot.egg-info/SOURCES.txt
amazon_buy_bot.egg-info/dependency_links.txt
amazon_buy_bot.egg-info/requires.txt
amazon_buy_bot.egg-info/top_level.txt