Metadata-Version: 2.1
Name: amazon-buy-bot
Version: 1.0.1
Summary: A python library to buy a product automatically on amazon.
Home-page: https://amazon-api.datakund.com/en/latest/
Author: DataKund
Author-email: datakund@gmail.com
License: Apache License 2.0
Keywords: amazon python bot_studio automation login checkout place-order product
Platform: UNKNOWN
